<?xml version="1.0" encoding="UTF-8"?>
<databaseChangeLog
        xmlns="http://www.liquibase.org/xml/ns/dbchangelog"
        xmlns:xsi="http://www.w3.org/2001/XMLSchema-instance"
        xsi:schemaLocation="http://www.liquibase.org/xml/ns/dbchangelog
    http://www.liquibase.org/xml/ns/dbchangelog/dbchangelog-4.3.xsd">

    <changeSet id="168077d7-0e2b-498a-add9-1b3282389cb4" author="hudsonalves">
        <createSequence
                sequenceName="user_seq"
                startValue="1"
                incrementBy="1"
                cycle="false"/>
    </changeSet>

    <changeSet id="607825bd-6ef7-4e4f-9c6b-6d5c289633f4" author="hudsonalves">
        <createTable tableName="users">
            <column name="id" type="BIGINT">
                <constraints primaryKey="true" nullable="false"/>
            </column>
            <column name="name" type="VARCHAR(255)">
                <constraints nullable="false"/>
            </column>
        </createTable>
    </changeSet>

</databaseChangeLog>
